spaceminator/__init__.py
spaceminator/app.py
spaceminator/main.py
spaceminator/tests/__init__.py
spaceminator/tests/test_app.py
spaceminator/tests/test_main.py
spaceminator-1.0.0.dist-info/DESCRIPTION.rst
spaceminator-1.0.0.dist-info/METADATA
spaceminator-1.0.0.dist-info/RECORD
spaceminator-1.0.0.dist-info/WHEEL
spaceminator-1.0.0.dist-info/entry_points.txt
spaceminator-1.0.0.dist-info/metadata.json
spaceminator-1.0.0.dist-info/top_level.txt
