Metadata-Version: 2.0
Name: spaceminator
Version: 1.0.0
Summary: spaceminator is a command line tool to help you get rid off those nasty spaces in your filenames!
Home-page: https://github.com/kchomski/spaceminator
Author: Krzysztof Chomski
Author-email: krzysztof.chomski@gmail.com
License: MIT
Platform: UNKNOWN
Classifier: Development Status :: 5 - Production/Stable
Classifier: Environment :: Console
Classifier: Intended Audience :: Developers
Classifier: License :: OSI Approved :: MIT License
Classifier: Operating System :: POSIX :: Linux
Classifier: Operating System :: Microsoft :: Windows
Classifier: Programming Language :: Python :: 2.7
Classifier: Programming Language :: Python :: 3.5
Classifier: Programming Language :: Python :: 3.6
Classifier: Topic :: Software Development
Classifier: Topic :: Utilities
Requires-Dist: pip
